odoo/addons/shopinvader_product_new/README.rst
odoo/addons/shopinvader_product_new/__init__.py
odoo/addons/shopinvader_product_new/__manifest__.py
odoo/addons/shopinvader_product_new/data/ir_cron.xml
odoo/addons/shopinvader_product_new/data/ir_export_product.xml
odoo/addons/shopinvader_product_new/i18n/shopinvader_product_new.pot
odoo/addons/shopinvader_product_new/models/__init__.py
odoo/addons/shopinvader_product_new/models/product_template.py
odoo/addons/shopinvader_product_new/readme/CONFIGURE.rst
odoo/addons/shopinvader_product_new/readme/CONTRIBUTORS.rst
odoo/addons/shopinvader_product_new/readme/CREDITS.rst
odoo/addons/shopinvader_product_new/readme/DESCRIPTION.rst
odoo/addons/shopinvader_product_new/static/description/index.html
odoo/addons/shopinvader_product_new/tests/__init__.py
odoo/addons/shopinvader_product_new/tests/test_product.py
odoo/addons/shopinvader_product_new/views/product_template.xml
odoo14_addon_shopinvader_product_new-14.0.1.0.1.dist-info/METADATA
odoo14_addon_shopinvader_product_new-14.0.1.0.1.dist-info/WHEEL
odoo14_addon_shopinvader_product_new-14.0.1.0.1.dist-info/top_level.txt
odoo14_addon_shopinvader_product_new-14.0.1.0.1.dist-info/RECORD
